ags_mcp/__init__.py
ags_mcp/client.py
ags_mcp/config.py
ags_mcp/errors.py
ags_mcp/http_server.py
ags_mcp/prompts.py
ags_mcp/stdio_server.py
ags_mcp/tools/__init__.py
ags_mcp/tools/dataset.py
ags_mcp/tools/graphmart.py
ags_mcp/tools/layer.py
ags_mcp/tools/ontology.py
ags_mcp/tools/pipeline.py
ags_mcp/tools/step.py
ags_mcp_server-1.0.0.dist-info/METADATA
ags_mcp_server-1.0.0.dist-info/WHEEL
ags_mcp_server-1.0.0.dist-info/entry_points.txt
ags_mcp_server-1.0.0.dist-info/top_level.txt
ags_mcp_server-1.0.0.dist-info/RECORD
